trippa/__init__.py
trippa/base.py
trippa/decorator.py
trippa/dependencies.py
trippa/exceptions.py
trippa/resolution.py
trippa/results.py
trippa/tasks.py
trippa/utils/__init__.py
trippa/utils/asyncio.py
trippa/utils/types.py
trippa-0.0.1.dist-info/METADATA
trippa-0.0.1.dist-info/WHEEL
trippa-0.0.1.dist-info/RECORD
