Metadata-Version: 2.1
Name: trippa
Version: 0.0.1
Summary: A library for defining and resolving a DAG of features in python
Author: Mauro Insacco
Author-email: mauro.insacco@gmail.com
Requires-Python: >=3.10,<4.0
Classifier: Programming Language :: Python :: 3
Classifier: Programming Language :: Python :: 3.10
Classifier: Programming Language :: Python :: 3.11
